{
  "schema_version": "1.0",
  "operation_id": "op-20260423090352-1180f321",
  "created_at": "2026-04-23T09:03:52",
  "request": {
    "user_text": "把下面内容写入到刚创建的txt:帝高阳之苗裔兮，朕皇考曰伯庸。\n摄提贞于孟陬兮，惟庚寅吾以降。\n皇览揆余初度兮，肇锡余以嘉名。\n名余曰正则兮，字余曰灵均。\n纷吾既有此内美兮，又重之以修能。\n扈江离与辟芷兮，纫秋兰以为佩。\n汩余若将不及兮，恐年岁之不吾与。\n朝搴阰之木兰兮，夕揽洲之宿莽。\n日月忽其不淹兮，春与秋其代序。\n惟草木之零落兮，恐美人之迟暮。(惟 通：唯)\n不抚壮而弃秽兮，何不改此度？(改此度 一作：改乎此度)\n乘骐骥以驰骋兮，来吾道夫先路！\n昔三后之纯粹兮，固众芳之所在。\n杂申椒与菌桂兮，岂惟纫夫蕙茝！",
    "profile": "debian-family",
    "intent": "generic_shell"
  },
  "target": {
    "mode": "ssh",
    "host": "124.222.119.109",
    "port": 22
  },
  "operation": {
    "command": "echo -e \"帝高阳之苗裔兮，朕皇考曰伯庸。\\n摄提贞于孟陬兮，惟庚寅吾以降。\\n皇览揆余初度兮，肇锡余以嘉名。\\n名余曰正则兮，字余曰灵均。\\n纷吾既有此内美兮，又重之以修能。\\n扈江离与辟芷兮，纫秋兰以为佩。\\n汩余若将不及兮，恐年岁之不吾与。\\n朝搴阰之木兰兮，夕揽洲之宿莽。\\n日月忽其不淹兮，春与秋其代序。\\n惟草木之零落兮，恐美人之迟暮。(惟 通：唯)\\n不抚壮而弃秽兮，何不改此度？(改此度 一作：改乎此度)\\n乘骐骥以驰骋兮，来吾道夫先路！\\n昔三后之纯粹兮，固众芳之所在。\\n杂申椒与菌桂兮，岂惟纫夫蕙茝！\" > shi.txt",
    "timeout_seconds": 60,
    "requires_confirmation": false
  },
  "risk": {
    "level": "low",
    "blocked": false,
    "requires_confirmation": false,
    "reason": "Allowed by default policy."
  },
  "status": "approved"
}